README.md
setup.cfg
setup.py
distributions/Binomialdistribution.py
distributions/Gaussiandistribution.py
distributions/Generaldistribution.py
distributions/__init__.py
distributions/setup.py
mech_sumedha_distributions.egg-info/PKG-INFO
mech_sumedha_distributions.egg-info/SOURCES.txt
mech_sumedha_distributions.egg-info/dependency_links.txt
mech_sumedha_distributions.egg-info/not-zip-safe
mech_sumedha_distributions.egg-info/top_level.txt